{
"type": "FeatureCollection",
"name": "SELECT",
"crs": { "type": "name", "properties": { "name": "urn:ogc:def:crs:OGC:1.3:CRS84" } },
"features": [
{ "type": "Feature", "properties": { "LAYER": "1615", "KETERANGAN": "Sekolah", "SumberData": "tanahair.indonesia.go.id" }, "geometry": { "type": "Point", "coordinates": [ 113.69265081183795, -7.877146776268197 ] } },
{ "type": "Feature", "properties": { "LAYER": "1615", "KETERANGAN": "Sekolah", "SumberData": "tanahair.indonesia.go.id" }, "geometry": { "type": "Point", "coordinates": [ 113.69335469371137, -7.883693228776366 ] } },
{ "type": "Feature", "properties": { "LAYER": "1615", "KETERANGAN": "Sekolah", "SumberData": "tanahair.indonesia.go.id" }, "geometry": { "type": "Point", "coordinates": [ 113.699738274453807, -7.885676185405789 ] } },
{ "type": "Feature", "properties": { "LAYER": "1455", "KETERANGAN": "Kuburan Islam", "SumberData": "tanahair.indonesia.go.id" }, "geometry": { "type": "Point", "coordinates": [ 113.701058017266263, -7.880968981062026 ] } },
{ "type": "Feature", "properties": { "LAYER": "1455", "KETERANGAN": "Kuburan Islam", "SumberData": "tanahair.indonesia.go.id" }, "geometry": { "type": "Point", "coordinates": [ 113.70088713257995, -7.881177956312692 ] } },
{ "type": "Feature", "properties": { "LAYER": "1455", "KETERANGAN": "Kuburan Islam", "SumberData": "tanahair.indonesia.go.id" }, "geometry": { "type": "Point", "coordinates": [ 113.70315863269478, -7.884886035879669 ] } },
{ "type": "Feature", "properties": { "LAYER": "1455", "KETERANGAN": "Kuburan Islam", "SumberData": "tanahair.indonesia.go.id" }, "geometry": { "type": "Point", "coordinates": [ 113.706322286266399, -7.882245192722636 ] } },
{ "type": "Feature", "properties": { "LAYER": "1455", "KETERANGAN": "Kuburan Islam", "SumberData": "tanahair.indonesia.go.id" }, "geometry": { "type": "Point", "coordinates": [ 113.701240624252151, -7.881184710217257 ] } },
{ "type": "Feature", "properties": { "LAYER": "1455", "KETERANGAN": "Kuburan Islam", "SumberData": "tanahair.indonesia.go.id" }, "geometry": { "type": "Point", "coordinates": [ 113.694232610197474, -7.879323306219869 ] } },
{ "type": "Feature", "properties": { "LAYER": "1455", "KETERANGAN": "Kuburan Islam", "SumberData": "tanahair.indonesia.go.id" }, "geometry": { "type": "Point", "coordinates": [ 113.703350535035938, -7.885128805150547 ] } },
{ "type": "Feature", "properties": { "LAYER": "1415", "KETERANGAN": "Masjid", "SumberData": "tanahair.indonesia.go.id" }, "geometry": { "type": "Point", "coordinates": [ 113.707968060043228, -7.880309952537785 ] } },
{ "type": "Feature", "properties": { "LAYER": "1415", "KETERANGAN": "Masjid", "SumberData": "tanahair.indonesia.go.id" }, "geometry": { "type": "Point", "coordinates": [ 113.692335669228882, -7.876055405124363 ] } },
{ "type": "Feature", "properties": { "LAYER": "1415", "KETERANGAN": "Masjid", "SumberData": "tanahair.indonesia.go.id" }, "geometry": { "type": "Point", "coordinates": [ 113.699283272190826, -7.882588845554812 ] } },
{ "type": "Feature", "properties": { "LAYER": "1415", "KETERANGAN": "Masjid", "SumberData": "tanahair.indonesia.go.id" }, "geometry": { "type": "Point", "coordinates": [ 113.695996772694969, -7.885862917192494 ] } },
{ "type": "Feature", "properties": { "LAYER": "1415", "KETERANGAN": "Masjid", "SumberData": "tanahair.indonesia.go.id" }, "geometry": { "type": "Point", "coordinates": [ 113.701264694348481, -7.887690409820522 ] } },
{ "type": "Feature", "properties": { "LAYER": "1365", "KETERANGAN": "Kantor Desa", "SumberData": "tanahair.indonesia.go.id" }, "geometry": { "type": "Point", "coordinates": [ 113.700605026447619, -7.885182665283865 ] } },
{ "type": "Feature", "properties": { "LAYER": "1215", "KETERANGAN": "Bangunan Terpencar", "SumberData": "tanahair.indonesia.go.id" }, "geometry": { "type": "Point", "coordinates": [ 113.714209490760922, -7.878561773089149 ] } },
{ "type": "Feature", "properties": { "LAYER": "1215", "KETERANGAN": "Bangunan Terpencar", "SumberData": "tanahair.indonesia.go.id" }, "geometry": { "type": "Point", "coordinates": [ 113.713420351562831, -7.878449444439554 ] } },
{ "type": "Feature", "properties": { "LAYER": "1215", "KETERANGAN": "Bangunan Terpencar", "SumberData": "tanahair.indonesia.go.id" }, "geometry": { "type": "Point", "coordinates": [ 113.713310558271047, -7.878296578606657 ] } },
{ "type": "Feature", "properties": { "LAYER": "1215", "KETERANGAN": "Bangunan Terpencar", "SumberData": "tanahair.indonesia.go.id" }, "geometry": { "type": "Point", "coordinates": [ 113.714400339465101, -7.875867881759573 ] } }
]
}
